arcor2_scene/VERSION
arcor2_scene/__init__.py
arcor2_scene/exceptions.py
arcor2_scene/py.typed
arcor2_scene/scripts/__init__.py
arcor2_scene/scripts/scene.py
arcor2_scene-1.1.0.dist-info/METADATA
arcor2_scene-1.1.0.dist-info/WHEEL
arcor2_scene-1.1.0.dist-info/entry_points.txt
arcor2_scene-1.1.0.dist-info/namespace_packages.txt
arcor2_scene-1.1.0.dist-info/top_level.txt
arcor2_scene-1.1.0.dist-info/RECORD
