Metadata-Version: 2.1
Name: arcor2-scene
Version: 1.1.0
Summary: ARCOR2 Scene Service
Author: Robo@FIT
Author-email: imaterna@fit.vut.cz
License: LGPL
Classifier: Development Status :: 3 - Alpha
Classifier: Intended Audience :: Developers
Classifier: Topic :: Software Development :: Build Tools
Classifier: License :: OSI Approved :: GNU Lesser General Public License v3 (LGPLv3)
Classifier: Programming Language :: Python :: 3.11
Classifier: Natural Language :: English
Classifier: Topic :: Scientific/Engineering
Requires-Python: ==3.11.*
Requires-Dist: Flask (~=3.0.2)
Requires-Dist: arcor2 (~=1.3.0)
Requires-Dist: numpy-quaternion[numba,scipy] (~=2023.0.3)
Requires-Dist: numpy (~=1.26.4)
Requires-Dist: open3d (==0.18.0)
Requires-Dist: pyhumps (==3.8.0)
